pycircuitbreaker/VERSION
pycircuitbreaker/__init__.py
pycircuitbreaker/exceptions.py
pycircuitbreaker/pycircuitbreaker.py
pycircuitbreaker/state.py
pycircuitbreaker/strategies/__init__.py
pycircuitbreaker/strategies/net_error.py
pycircuitbreaker/strategies/single_reset.py
pycircuitbreaker-0.5.0.dist-info/LICENSE
pycircuitbreaker-0.5.0.dist-info/METADATA
pycircuitbreaker-0.5.0.dist-info/WHEEL
pycircuitbreaker-0.5.0.dist-info/top_level.txt
pycircuitbreaker-0.5.0.dist-info/RECORD
