Metadata-Version: 2.1
Name: pycircuitbreaker
Version: 0.5.0
Summary: Python implementation of the Circuit Breaker Pattern
Home-page: https://github.com/etimberg/pycircuitbreaker
Author: Evert Timberg
Author-email: evert@everttimberg.io
License: MIT
Platform: any
Classifier: Development Status :: 3 - Alpha
Classifier: License :: OSI Approved :: MIT License
Classifier: Intended Audience :: Developers
Classifier: Topic :: Software Development :: Libraries :: Python Modules
Classifier: Programming Language :: Python :: 3
Classifier: Programming Language :: Python :: 3.6
Classifier: Programming Language :: Python :: 3.7
Classifier: Programming Language :: Python :: 3.8
Provides-Extra: test
Requires-Dist: pytest (>=5.3) ; extra == 'test'
Requires-Dist: pytest-cov ; extra == 'test'
